django_migrant/__init__.py
django_migrant/__main__.py
django_migrant/hook_templates/header
django_migrant/hook_templates/post-checkout
django_migrant/hook_templates/pre-rebase
django_migrant/management/__init__.py
django_migrant/management/commands/__init__.py
django_migrant/management/commands/migrant.py
django_migrant-0.0.9.dist-info/licenses/LICENSE.txt
django_migrant-0.0.9.dist-info/METADATA
django_migrant-0.0.9.dist-info/WHEEL
django_migrant-0.0.9.dist-info/top_level.txt
django_migrant-0.0.9.dist-info/RECORD
