Metadata-Version: 2.4
Name: django-migrant
Version: 0.0.9
Summary: A developer utility to auto-migrate django apps when switching git branches.
Author: Paul Backhouse
License-Expression: GPL-3.0-only
Project-URL: Homepage, https://github.com/powlo/django-migrant
Project-URL: Bug Tracker, https://github.com/powlo/django-migrant/issues
Keywords: django,developer,migration,tool,git
Classifier: Programming Language :: Python :: 3
Classifier: Operating System :: OS Independent
Requires-Python: >=3.7
License-File: LICENSE.txt
Requires-Dist: django
Dynamic: license-file
